veroviz/__init__.py
veroviz/_buildFlightProfile.py
veroviz/_common.py
veroviz/_createAssignments.py
veroviz/_createEntitiesFromList.py
veroviz/_deconstructAssignments.py
veroviz/_elevation.py
veroviz/_geocode.py
veroviz/_geometry.py
veroviz/_getShapepoints.py
veroviz/_getSnapLoc.py
veroviz/_getTimeDistFromLocs2D.py
veroviz/_internal.py
veroviz/_isochrones.py
veroviz/_nearestNodes.py
veroviz/_params.py
veroviz/_queryElevationapiio.py
veroviz/_queryMapQuest.py
veroviz/_queryORS.py
veroviz/_queryORSlocal.py
veroviz/_queryOSRM.py
veroviz/_queryOpenWeather.py
veroviz/_queryPgRouting.py
veroviz/_queryUSGS.py
veroviz/_utilities.py
veroviz/_validation.py
veroviz/_weather.py
veroviz/createAssignments.py
veroviz/createCesium.py
veroviz/createLeaflet.py
veroviz/generateArcs.py
veroviz/generateNodes.py
veroviz/getShapepoints2D.py
veroviz/getShapepoints3D.py
veroviz/getTimeDist2D.py
veroviz/getTimeDist3D.py
veroviz/getTimeDistScalar2D.py
veroviz/getTimeDistScalar3D.py
veroviz/snapNodesToRoad.py
veroviz/utilities.py
veroviz-0.4.6.dist-info/licenses/LICENSE.md
veroviz-0.4.6.dist-info/METADATA
veroviz-0.4.6.dist-info/WHEEL
veroviz-0.4.6.dist-info/top_level.txt
veroviz-0.4.6.dist-info/RECORD
