Metadata-Version: 2.4
Name: veroviz
Version: 0.4.6
Summary: VeRoViz: Vehicle Routing Visualization
Home-page: https://veroviz.org
Download-URL: https://github.com/optimatorlab/veroviz
Author: Chase Murray, Lan Peng
Author-email: cmurray3@buffalo.edu, lanpeng@buffalo.edu
License: MIT
Project-URL: Bug Tracker, https://github.com/optimatorlab/veroviz/issues
Project-URL: Documentation, https://veroviz.org
Project-URL: Source Code, https://github.com/optimatorlab/veroviz
Classifier: Development Status :: 2 - Pre-Alpha
Classifier: Programming Language :: Python :: 2.7
Classifier: Programming Language :: Python :: 3
Classifier: Topic :: Scientific/Engineering :: Visualization
Classifier: License :: OSI Approved :: MIT License
Classifier: Operating System :: OS Independent
Requires-Python: >=2.7
License-File: LICENSE.md
Requires-Dist: numpy
Requires-Dist: pandas
Requires-Dist: geopy
Requires-Dist: psycopg2-binary
Requires-Dist: urllib3
Requires-Dist: folium
Requires-Dist: tripy
Requires-Dist: scipy
Requires-Dist: matplotlib
Dynamic: author
Dynamic: author-email
Dynamic: classifier
Dynamic: description
Dynamic: description-content-type
Dynamic: download-url
Dynamic: home-page
Dynamic: license
Dynamic: license-file
Dynamic: project-url
Dynamic: requires-dist
Dynamic: requires-python
Dynamic: summary
